README.rst
distribute_setup.py
setup.py
benchmark/__init__.py
benchmark/dumps.py
benchmark/loads.py
cpghstore.egg-info/PKG-INFO
cpghstore.egg-info/SOURCES.txt
cpghstore.egg-info/dependency_links.txt
cpghstore.egg-info/top_level.txt
src/cpghstore.c
tests/__init__.py
tests/dumps.py
tests/loads.py