Metadata-Version: 1.0
Name: cpghstore
Version: 0.1
Summary: Fast postgres hstore parser.
Home-page: https://github.com/kajic/cpghstore
Author: Robert Kajic
Author-email: robert@{nospam}kajic.com
License: MIT
Platform: any
Classifier: Development Status :: 4 - Beta
Classifier: Intended Audience :: Developers
Classifier: License :: OSI Approved :: MIT License
Classifier: Operating System :: OS Independent
Classifier: Programming Language :: C
Classifier: Programming Language :: Python
Classifier: Topic :: Database
Classifier: Topic :: Software Development :: Libraries :: Python Modules
